{
    "times_nba": [
      {
        "id": 1,
        "nome": "Los Angeles Lakers",
        "jogadores": [
          {
            "nome": "LeBron James",
            "draft_photo_url": "https://upload.wikimedia.org/wikipedia/commons/thumb/3/39/LeBron_James_and_Kevin_Love_%28cropped%29.jpg/640px-LeBron_James_and_Kevin_Love_%28cropped%29.jpg"
          },
          {
            "nome": "Magic Johnson",
            "draft_photo_url": "https://cdn.britannica.com/27/189527-050-5BAD12C2/Magic-Johnson.jpg"
          },
          {
            "nome": "Kobe Bryant",
            "draft_photo_url": "https://upload.wikimedia.org/wikipedia/commons/5/56/Kobe_Bryant_2014.jpg"
          }
        ]
      },
      {
        "id": 2,
        "nome": "Boston Celtics",
        "jogadores": [
          {
            "nome": "Larry Bird",
            "draft_photo_url": "https://cdn.britannica.com/60/258260-050-35DB0395/larry-bird-of-boston-celtics-shoots-free-throw-against-the-washington-bullets-1985.jpg"
          },
          {
            "nome": "Paul Pierce",
            "draft_photo_url": "https://upload.wikimedia.org/wikipedia/commons/5/58/Paul_Pierce_2008-01-13.jpg"
          },
          {
            "nome": "Bill Russell",
            "draft_photo_url": "https://cdn.britannica.com/65/234465-050-A5ECD52A/Bill-Russell-Boston-Celtics-undated-photo.jpg"
          }
        ]
      },
      {
        "id": 3,
        "nome": "Golden State Warriors",
        "jogadores": [
          {
            "nome": "Stephen Curry",
            "draft_photo_url": "https://hips.hearstapps.com/hmg-prod/images/stephen-curry-gettyimages-1398745379.jpg"
          },
          {
            "nome": "Kevin Durant",
            "draft_photo_url": "https://e0.365dm.com/18/12/2048x1152/skysports-kevin-durant-golden-state-warriors_4510337.jpg?20181206083205"
          },
          {
            "nome": "Klay Thompson",
            "draft_photo_url": "https://lncimg.lance.com.br/cdn-cgi/image/width=1280,height=720,quality=75,format=webp/uploads/2024/07/Klay-Thompson-5-aspect-ratio-512-320.jpg"
          }
        ]
      },
      {
        "id": 4,
        "nome": "Chicago Bulls",
        "jogadores": [
          {
            "nome": "Michael Jordan",
            "draft_photo_url": "https://encrypted-tbn0.gstatic.com/images?q=tbn:ANd9GcQWMzBOvRSYNbchM69HgUffECIMuMjFq87ywnhR6Xk_9fIlGwbG"
          },
          {
            "nome": "Scottie Pippen",
            "draft_photo_url": "https://bullsbrasil.wordpress.com/wp-content/uploads/2010/02/pippen.jpg"
          },
          {
            "nome": "Derrick Rose",
            "draft_photo_url": "https://encrypted-tbn2.gstatic.com/images?q=tbn:ANd9GcRlIVcUGZavMYaQosSokCRbogyaVqPgzlF6JGGlZMNjbu5lOAxN"
          }
        ]
      },
      {
        "id": 5,
        "nome": "Miami Heat",
        "jogadores": [
          {
            "nome": "Dwyane Wade",
            "draft_photo_url": "https://media-cldnry.s-nbcnews.com/image/upload/t_fit-760w,f_auto,q_auto:best/msnbc/Components/Photos/061224/061224_wade_vlrg_12p.jpg"
          },
          {
            "nome": "LeBron James",
            "draft_photo_url": "https://jpimg.com.br/uploads/2017/04/H_20111219_123117-3.jpg"
          },
          {
            "nome": "Shaquille O'Neal",
            "draft_photo_url": "https://images.futebolinterior.com.br/2021/04/0002050210864_img.jpg"
          }
        ]
      },
      {
        "id": 6,
        "nome": "San Antonio Spurs",
        "jogadores": [
          {
            "nome": "Tim Duncan",
            "draft_photo_url": "https://upload.wikimedia.org/wikipedia/commons/1/14/Tim_Duncan.jpg"
          },
          {
            "nome": "Tony Parker",
            "draft_photo_url": "https://upload.wikimedia.org/wikipedia/commons/thumb/c/c4/Parker_khomar.JPG/1200px-Parker_khomar.JPG"
          },
          {
            "nome": "Manu Ginobili",
            "draft_photo_url": "https://upload.wikimedia.org/wikipedia/commons/b/ba/Manu_Gin%C3%B3bili_%28cropped_2%29.jpg"
          }
        ]
      },
      {
        "id": 7,
        "nome": "Houston Rockets",
        "jogadores": [
          {
            "nome": "Hakeem Olajuwon",
            "draft_photo_url": "https://encrypted-tbn3.gstatic.com/images?q=tbn:ANd9GcSGW-S0TNS1QiCyC1NbJ78C6BuumyQrPGtm-qUEPdcme4y8u1Oo"
          },
          {
            "nome": "Tracy McGrady",
            "draft_photo_url": "https://upload.wikimedia.org/wikipedia/commons/thumb/f/f9/Tracy_McGrady_1.jpg/640px-Tracy_McGrady_1.jpg"
          },
          {
            "nome": "Yao Ming",
            "draft_photo_url": "https://upload.wikimedia.org/wikipedia/commons/thumb/a/a7/YaoMingonoffense2.jpg/1200px-YaoMingonoffense2.jpg"
          }
        ]
      },
      {
        "id": 8,
        "nome": "Dallas Mavericks",
        "jogadores": [
          {
            "nome": "Dirk Nowitzki",
            "draft_photo_url": "https://www.usatoday.com/gcdn/-mm-/ad07fc0628987cc179f39e4ceddb377d02845c02/c=0-40-2272-3069/local/-/media/2017/03/08/USATODAY/USATODAY/636245933357106206-USATSI-9856648.jpg"
          },
          {
            "nome": "Jason Kidd",
            "draft_photo_url": "https://cdn.vox-cdn.com/thumbor/GmEjfAv0QMvEVw0DaT2zODOtKaY=/0x0:3000x2001/1200x800/filters:focal(1260x761:1740x1241)/cdn.vox-cdn.com/uploads/chorus_image/image/69502672/143139329.0.jpg"
          },
          {
            "nome": "Luka Dončić",
            "draft_photo_url": "https://upload.wikimedia.org/wikipedia/commons/6/6c/Luka_Doncic_2021_%28cropped%29.jpg"
          }
        ]
      }
    ]
  }
  